{
  "name": "collections/blog/posts/4508c1a3b966",
  "__resolveType": "blog/loaders/Blogpost.ts",
  "post": {
    "authors": [],
    "categories": [
      {
        "name": "Na Mídia",
        "slug": "na-midia"
      }
    ],
    "imageCarousel": {
      "banners": []
    },
    "extraProps": [
      {
        "key": "url",
        "value": "https://tinyurl.com/mn4bw3e7"
      }
    ],
    "aggregateRating": {
      "@type": "AggregateRating"
    },
    "review": [],
    "contentRating": [],
    "interactionStatistic": {
      "@type": "InteractionCounter",
      "video": null,
      "image": null
    },
    "title": "Jornal Hoje: Série sobre a expansão das milícias no Rio de Janeiro",
    "excerpt": "Joana Monteiro, diretora do Leme, em entrevista ao Jornal Hoje.",
    "content": "<p><span style=\"color: rgb(42, 50, 44); font-size: 16px\">Joana Monteiro, diretora do Leme, em entrevista ao Jornal Hoje.</span></p>",
    "slug": "na-midia-6",
    "image": "https://assets.decocache.com/novo-leme/778a79d7-54c5-41e6-956c-9a66d9d59fe9/na-midia-6.webp",
    "date": "2023-08-18"
  }
}